{
  "hash": "7622a1d7",
  "configHash": "5f799061",
  "lockfileHash": "9430f130",
  "browserHash": "bafe9b74",
  "optimized": {
    "vue": {
      "src": "../../../../node_modules/vue/dist/vue.runtime.esm-bundler.js",
      "file": "vue.js",
      "fileHash": "941bbc94",
      "needsInterop": false
    },
    "vitepress > @vue/devtools-api": {
      "src": "../../../../node_modules/@vue/devtools-api/dist/index.js",
      "file": "vitepress___@vue_devtools-api.js",
      "fileHash": "dde18dfb",
      "needsInterop": false
    },
    "vitepress > @vueuse/core": {
      "src": "../../../../node_modules/@vueuse/core/index.mjs",
      "file": "vitepress___@vueuse_core.js",
      "fileHash": "eb7fbc92",
      "needsInterop": false
    },
    "@fortawesome/fontawesome-svg-core": {
      "src": "../../../../node_modules/@fortawesome/fontawesome-svg-core/index.mjs",
      "file": "@fortawesome_fontawesome-svg-core.js",
      "fileHash": "db6fedf0",
      "needsInterop": false
    },
    "@fortawesome/free-solid-svg-icons": {
      "src": "../../../../node_modules/@fortawesome/free-solid-svg-icons/index.mjs",
      "file": "@fortawesome_free-solid-svg-icons.js",
      "fileHash": "919a9b24",
      "needsInterop": false
    },
    "@vitepress-demo-preview/component": {
      "src": "../../../../node_modules/@vitepress-demo-preview/component/dist/preview-component.js",
      "file": "@vitepress-demo-preview_component.js",
      "fileHash": "6290c0c8",
      "needsInterop": false
    },
    "lodash-es": {
      "src": "../../../../node_modules/lodash-es/lodash.js",
      "file": "lodash-es.js",
      "fileHash": "d342655f",
      "needsInterop": false
    },
    "@fortawesome/vue-fontawesome": {
      "src": "../../../../node_modules/@fortawesome/vue-fontawesome/index.es.js",
      "file": "@fortawesome_vue-fontawesome.js",
      "fileHash": "d5f17325",
      "needsInterop": false
    },
    "@popperjs/core": {
      "src": "../../../../node_modules/@popperjs/core/lib/index.js",
      "file": "@popperjs_core.js",
      "fileHash": "332c84ad",
      "needsInterop": false
    }
  },
  "chunks": {
    "chunk-RZDVYSLR": {
      "file": "chunk-RZDVYSLR.js"
    },
    "chunk-RY5ODQAQ": {
      "file": "chunk-RY5ODQAQ.js"
    }
  }
}